{
  "status": 0,
  "message": "ok",
  "type": 2,
  "info": {
    "copyright": {
      "text": "@2016 Baidu - Data",
      "imageUrl": "http://api.map.baidu.com/images/copyright_logo.png"
    }
  },
  "result": {
    "routes": [
      {
        "distance": 4169,
        "duration": 1170,
        "steps": [
          {
            "area": 0,
            "direction": 6,
            "distance": 420,
            "duration": 145,
            "instructions": "从起点\u003c/b\u003e向正南方向出发,沿较场西路\u003c/b\u003e行驶380米,过左侧的置地大厦\u003c/font\u003e\u003c/b\u003e右转\u003c/b\u003e进入东华西路\u003c/b\u003e",
            "path": "113.2896425124,23.131941102561;113.2896425124,23.131881198631;113.28964260223,23.13165130355;113.28962283951,23.131041460672;113.289623109,23.130291615961;113.28962319883,23.130141729595;113.2896134073,23.129681849916;113.2896134073,23.129631915279;113.28961349713,23.129441980696;113.28961358696,23.12919205761;113.28961358696,23.129122182089;113.28960388526,23.128602310377;113.28959418356,23.128162449294",
            "pois": [
              {
                "detail": {
                  "instructions": "",
                  "position": 0
                },
                "location": {
                  "lng": 113.28980375824,
                  "lat": 23.128540826294
                },
                "name": "置地大厦",
                "type": 106
              }
            ],
            "turn": 3,
            "type": 3,
            "stepOriginLocation": {
              "lng": 113.2896425124,
              "lat": 23.131941102561
            },
            "stepDestinationLocation": {
              "lng": 113.28959373441,
              "lat": 23.128161535339
            },
            "stepOriginInstruction": "从起点向正南方向出发 - 540米",
            "stepDestinationInstruction": "右转进入东华西路 - 540米",
            "traffic_condition": 1
          },
          {
            "area": 0,
            "direction": 9,
            "distance": 540,
            "duration": 175,
            "instructions": "沿东华西路\u003c/b\u003e行驶430米,过左侧的喜尔宾酒店-商务中心\u003c/font\u003e\u003c/b\u003e约120米后,直行\u003c/b\u003e进入文明路\u003c/b\u003e",
            "path": "113.2888933256,23.128343329255;113.28845324573,23.128374237519;113.28759302838,23.128455496309;113.28707299932,23.128495959512;113.28637303966,23.128546143837;113.28620317009,23.128566084624;113.28580324448,23.128605966187;113.28570335291,23.128635877351;113.28566346814,23.128665871596;113.28516356113,23.128825397657;113.28508370177,23.128845338401;113.28500384241,23.128865196056;113.28497392883,23.128875166425;113.28451408624,23.129014419173;113.28444419807,23.129044330246",
            "pois": [
              {
                "detail": {
                  "instructions": "",
                  "position": 0
                },
                "location": {
                  "lng": 113.28442290823,
                  "lat": 23.128764329109
                },
                "name": "喜尔宾酒店-商务中心",
                "type": 106
              }
            ],
            "turn": 1,
            "type": 3,
            "stepOriginLocation": {
              "lng": 113.28959373441,
              "lat": 23.128161535339
            },
            "stepDestinationLocation": {
              "lng": 113.28444285061,
              "lat": 23.129044330246
            },
            "stepOriginInstruction": "",
            "stepDestinationInstruction": "直行进入文明路 - 610米",
            "traffic_condition": 1
          },
          {
            "area": 0,
            "direction": 9,
            "distance": 611,
            "duration": 191,
            "instructions": "沿文明路\u003c/b\u003e行驶320米,过右侧的百美百货店\u003c/font\u003e\u003c/b\u003e约300米后,右转\u003c/b\u003e进入文德路\u003c/b\u003e",
            "path": "113.28389308764,23.129043167038;113.28381322828,23.129043083951;113.28318369578,23.129061362937;113.28265414468,23.129069671566;113.28226454958,23.129068342185;113.28223463601,23.129068342185;113.28180506632,23.129076567727;113.28164525777,23.129065932683;113.28131566947,23.129074407484;113.28102605578,23.129073078104;113.28040676396,23.129079808092;113.28025701643,23.129069089962;113.28011724009,23.12905837183;113.27993757899,23.129047404439;113.27963808394,23.129025635826;113.27946839402,23.129004614987;113.27940856688,23.128994312282;113.27937874313,23.128984175749;113.27913916506,23.128942715658;113.27854017494,23.128728685005",
            "pois": [
              {
                "detail": {
                  "instructions": "",
                  "position": 1
                },
                "location": {
                  "lng": 113.28135483559,
                  "lat": 23.129114288894
                },
                "name": "百美百货店",
                "type": 104
              }
            ],
            "turn": 3,
            "type": 3,
            "stepOriginLocation": {
              "lng": 113.28444285061,
              "lat": 23.129044330246
            },
            "stepDestinationLocation": {
              "lng": 113.27853837833,
              "lat": 23.128727604881
            },
            "stepOriginInstruction": "",
            "stepDestinationInstruction": "右转进入文德路 - 400米",
            "traffic_condition": 1
          },
          {
            "area": 0,
            "direction": 11,
            "distance": 398,
            "duration": 101,
            "instructions": "沿文德路\u003c/b\u003e行驶400米,左转\u003c/b\u003e进入中山四路\u003c/b\u003e",
            "path": "113.27824849514,23.129485434695;113.27794873059,23.130313135109;113.27791881702,23.130362903319;113.27785890004,23.130552421156;113.27776906949,23.130851694278;113.27773915592,23.130981473251;113.27749939818,23.131979487588;113.27750936937,23.132089574458;113.27742959984,23.132079022739",
            "pois": [],
            "turn": 7,
            "type": 3,
            "stepOriginLocation": {
              "lng": 113.27853837833,
              "lat": 23.128727604881
            },
            "stepDestinationLocation": {
              "lng": 113.27742906086,
              "lat": 23.132078939655
            },
            "stepOriginInstruction": "",
            "stepDestinationInstruction": "左转进入中山四路 - 230米",
            "traffic_condition": 1
          },
          {
            "area": 0,
            "direction": 9,
            "distance": 225,
            "duration": 43,
            "instructions": "沿中山四路\u003c/b\u003e行驶180米,过左侧的广百黄金珠宝大厦\u003c/font\u003e\u003c/b\u003e朝中山五路/吉祥路方向\u003c/b\u003e,进入中山五路\u003c/b\u003e",
            "path": "113.27737911507,23.132078524233;113.27593176523,23.13200599153;113.27530313104,23.131960045822;113.27524330389,23.131959547316",
            "pois": [
              {
                "detail": {
                  "instructions": "",
                  "position": 0
                },
                "location": {
                  "lng": 113.27574213294,
                  "lat": 23.131754162331
                },
                "name": "广百黄金珠宝大厦",
                "type": 106
              }
            ],
            "turn": 1,
            "type": 3,
            "stepOriginLocation": {
              "lng": 113.27742906086,
              "lat": 23.132078939655
            },
            "stepDestinationLocation": {
              "lng": 113.2752430344,
              "lat": 23.131959381147
            },
            "stepOriginInstruction": "",
            "stepDestinationInstruction": "进入中山五路 - 680米",
            "traffic_condition": 1
          },
          {
            "area": 0,
            "direction": 9,
            "distance": 679,
            "duration": 143,
            "instructions": "沿中山五路\u003c/b\u003e行驶530米,过右侧的麦当劳(动漫星城店)\u003c/font\u003e\u003c/b\u003e约150米后,直行\u003c/b\u003e进入中山六路\u003c/b\u003e",
            "path": "113.27487383083,23.131935618984;113.27462446122,23.13192315631;113.27437509161,23.13191061055;113.27397606431,23.131896403098;113.27300840961,23.131845638449;113.27273909762,23.131832594175;113.27193116165,23.131792962836;113.27185148195,23.131782078755;113.27106357818,23.131752251385;113.27066473054,23.131727159831;113.27063490679,23.131736797647;113.27051534233,23.13172533197;113.27045560502,23.131724584208;113.27041581008,23.131724168785;113.2698275098,23.131706305589;113.2697478301,23.131705308574;113.2696781216,23.131704394643;113.26878080422,23.131651885142;113.26875098048,23.131651552804;113.26866132959,23.131630366211;113.26863150585,23.131619980625",
            "pois": [
              {
                "detail": {
                  "instructions": "",
                  "position": 1
                },
                "location": {
                  "lng": 113.2701053557,
                  "lat": 23.131959048809
                },
                "name": "麦当劳(动漫星城店)",
                "type": 109
              }
            ],
            "turn": 1,
            "type": 3,
            "stepOriginLocation": {
              "lng": 113.2752430344,
              "lat": 23.131959381147
            },
            "stepDestinationLocation": {
              "lng": 113.26862961941,
              "lat": 23.131618568186
            },
            "stepOriginInstruction": "",
            "stepDestinationInstruction": "直行进入中山六路 - 650米",
            "traffic_condition": 1
          },
          {
            "area": 0,
            "direction": 9,
            "distance": 651,
            "duration": 165,
            "instructions": "沿中山六路\u003c/b\u003e行驶620米,过右侧的捷泰广场\u003c/font\u003e\u003c/b\u003e调头\u003c/b\u003e",
            "path": "113.26800152419,23.131579435291;113.26762279859,23.131543958113;113.26687522875,23.131512801333;113.26655633029,23.131498012246;113.26635708613,23.131485051021;113.2658189113,23.131456719111;113.26532062123,23.131418915525;113.26487218712,23.131391829873;113.26468291415,23.131388838819;113.26431424957,23.131362916348;113.26403523588,23.131368316863;113.26398546975,23.131367569099;113.26298897945,23.131361088481;113.26243095207,23.131361670075;113.26242107071,23.131251582602",
            "pois": [
              {
                "detail": {
                  "instructions": "",
                  "position": 1
                },
                "location": {
                  "lng": 113.26261896741,
                  "lat": 23.131553845196
                },
                "name": "捷泰广场",
                "type": 106
              }
            ],
            "turn": 5,
            "type": 3,
            "stepOriginLocation": {
              "lng": 113.26862961941,
              "lat": 23.131618568186
            },
            "stepDestinationLocation": {
              "lng": 113.26241972325,
              "lat": 23.131250419413
            },
            "stepOriginInstruction": "",
            "stepDestinationInstruction": "调头 - 160米",
            "traffic_condition": 1
          },
          {
            "area": 0,
            "direction": 3,
            "distance": 159,
            "duration": 47,
            "instructions": "继续沿中山六路\u003c/b\u003e行驶100米,过右侧的伦文叙纪念广场\u003c/font\u003e\u003c/b\u003e约60米后,右转\u003c/b\u003e进入海珠中路\u003c/b\u003e",
            "path": "113.2639644494,23.131256318442",
            "pois": [
              {
                "detail": {
                  "instructions": "",
                  "position": 1
                },
                "location": {
                  "lng": 113.26341630338,
                  "lat": 23.131177221577
                },
                "name": "伦文叙纪念广场",
                "type": 110
              }
            ],
            "turn": 3,
            "type": 3,
            "stepOriginLocation": {
              "lng": 113.26241972325,
              "lat": 23.131250419413
            },
            "stepDestinationLocation": {
              "lng": 113.2639644494,
              "lat": 23.131256318442
            },
            "stepOriginInstruction": "",
            "stepDestinationInstruction": "右转进入海珠中路 - 220米",
            "traffic_condition": 1
          },
          {
            "area": 0,
            "direction": 6,
            "distance": 218,
            "duration": 83,
            "instructions": "沿海珠中路\u003c/b\u003e行驶220米,左转\u003c/b\u003e进入光塔路\u003c/b\u003e",
            "path": "113.26392465447,23.131025674512;113.26389483073,23.130935277934;113.26377544592,23.130473406957;113.26370582725,23.130162334826;113.26364617976,23.129941410025;113.26361644585,23.129800995048;113.26350703224,23.129329315959",
            "pois": [],
            "turn": 7,
            "type": 2,
            "stepOriginLocation": {
              "lng": 113.2639644494,
              "lat": 23.131256318442
            },
            "stepDestinationLocation": {
              "lng": 113.26350658308,
              "lat": 23.129328817442
            },
            "stepOriginInstruction": "",
            "stepDestinationInstruction": "左转进入光塔路 - 270米",
            "traffic_condition": 1
          },
          {
            "area": 0,
            "direction": 4,
            "distance": 268,
            "duration": 71,
            "instructions": "沿光塔路\u003c/b\u003e行驶270米,到达终点\u003c/b\u003e",
            "path": "113.26415453085,23.129139547115;113.26422432919,23.129130739973;113.26469279551,23.128988496238;113.26476259385,23.128959748362;113.26527094494,23.128888044818;113.26534074327,23.12886926729;113.2656098756,23.128823652841;113.26595877746,23.128719213144;113.26598869104,23.128689800517",
            "pois": [],
            "turn": 0,
            "type": 2,
            "stepOriginLocation": {
              "lng": 113.26350658308,
              "lat": 23.129328817442
            },
            "stepDestinationLocation": {
              "lng": 113.26598869104,
              "lat": 23.128689052738
            },
            "stepDestinationInstruction": "到达终点",
            "traffic_condition": 1
          }
        ],
        "toll": 0,
        "originLocation": {
          "lng": 113.2896425124,
          "lat": 23.131941102561
        },
        "destinationLocation": {
          "lng": 113.26598869104,
          "lat": 23.128689052738
        }
      }
    ],
    "origin": {
      "area_id": 257,
      "bid": "18011961038232092671",
      "cname": "广州市",
      "uid": "28e700f1d95acb01095cb300",
      "wd": "富一城",
      "originPt": {
        "lng": 113.28963766155,
        "lat": 23.131946669221
      }
    },
    "destination": {
      "area_id": 257,
      "bid": "10647474",
      "cname": "广州市",
      "uid": "85f1a7fea9cfa740cb09f06b",
      "wd": "甜水巷",
      "destinationPt": {
        "lng": 113.26599426053,
        "lat": 23.128689717431
      }
    },
    "taxi": {
      "detail": [
        {
          "desc": "全天",
          "km_price": "2.6",
          "start_price": "10.0",
          "total_price": "15"
        }
      ],
      "distance": 4169,
      "duration": 1171,
      "remark": "全程4.2公里;2.5公里起步；燃油附加费0.0元；里程超过35.0公里，超过部分每公里收3.9元。"
    },
    "traffic_condition": 1
  }
}