{
  "status": 0,
  "message": "ok",
  "type": 1,
  "info": {
    "copyright": {
      "text": "@2016 Baidu - Data",
      "imageUrl": "http://api.map.baidu.com/images/copyright_logo.png"
    }
  },
  "result": {
    "originInfo": {
      "area_id": 257,
      "wd": "朗豪酒店",
      "uid": ""
    },
    "destinationInfo": {
      "area_id": 257,
      "wd": "金沙路",
      "uid": ""
    },
    "origin": {
      "cityName": "广州市",
      "listType": 0,
      "content": [
        {
          "name": "朗豪酒店",
          "address": "广州市海珠区新港东路638号南丰国际会展中心",
          "uid": "db1f39d4b3583e76f5c59c22",
          "location": {
            "lng": 113.36671739462,
            "lat": 23.102542387341
          }
        },
        {
          "name": "广州朗豪大酒店",
          "address": "广州市花都区花山镇团结路自编298号",
          "uid": "019d816f96e5ece3bb17e7a4",
          "telephone": "18026387357",
          "location": {
            "lng": 113.29388700593,
            "lat": 23.389225050431
          }
        }
      ]
    },
    "destination": {
      "cityName": "广州市",
      "listType": 0,
      "content": [
        {
          "name": "金沙路",
          "address": "广东省广州市海珠区",
          "uid": "0d123ad282e57f532f4733ff",
          "location": {
            "lng": 113.25938641503,
            "lat": 23.095949172202
          }
        },
        {
          "name": "金沙路",
          "address": "广东省广州市南沙区",
          "uid": "4e156a191cd504ab461a32ff",
          "location": {
            "lng": 113.56141253756,
            "lat": 22.826555376352
          }
        },
        {
          "name": "金沙路",
          "address": "广东省广州市白云区",
          "uid": "5234650650e300ad2dfaa797",
          "location": {
            "lng": 113.3869740042,
            "lat": 23.341610713876
          }
        },
        {
          "name": "革新路/金沙路(路口)",
          "address": "广东省广州市海珠区",
          "uid": "5e2dbb6ccefd1b578bb988c3",
          "location": {
            "lng": 113.26095377849,
            "lat": 23.096080647447
          }
        },
        {
          "name": "金沙路",
          "address": "",
          "uid": "bf810e083d755495077ce82c",
          "location": {
            "lng": 113.26261249961,
            "lat": 23.09620397809
          }
        },
        {
          "name": "金沙路",
          "address": "广东省广州市增城区",
          "uid": "bb2e6c7d2e2bce8caa059df5",
          "location": {
            "lng": 113.68446467204,
            "lat": 23.172533787381
          }
        },
        {
          "name": "金沙路/进港大道(路口)",
          "address": "广东省广州市南沙区",
          "uid": "bba87388361716a1bca822f5",
          "location": {
            "lng": 113.55282419791,
            "lat": 22.806515839541
          }
        },
        {
          "name": "金沙路/裕乐街(路口)",
          "address": "广东省广州市南沙区",
          "uid": "e116be54da755e7ac91b9504",
          "location": {
            "lng": 113.55290001489,
            "lat": 22.808774232061
          }
        },
        {
          "name": "金沙路金满楼",
          "address": "广州市越秀区正平南街3号",
          "uid": "bb1d75e8c38e5c5ff942b267",
          "location": {
            "lng": 113.2963438715,
            "lat": 23.14841083143
          }
        },
        {
          "name": "020 Salon（金沙路店）",
          "address": "金沙路16号1-2楼（近革新路）",
          "uid": "680fb7037bc872858bb98815",
          "telephone": "(020)84305575",
          "location": {
            "lng": 113.26124249388,
            "lat": 23.096325563376
          }
        },
        {
          "name": "小屋(金沙路店)",
          "address": "金沙洲城西花园翠林街89号铺",
          "uid": "dc570bda0ff6e62cb8bd6351",
          "telephone": "13229163120",
          "location": {
            "lng": 113.21516301445,
            "lat": 23.1637559008
          }
        },
        {
          "name": "味霸盐焗食品(金沙路店)",
          "address": "革新路119号之10号铺首层自编之二",
          "uid": "dbb5e6bd2802d3473904b1f5",
          "telephone": "13660441686",
          "location": {
            "lng": 113.26135999224,
            "lat": 23.095986985892
          }
        },
        {
          "name": "塞飞洛(金沙路)",
          "address": "金洲进港大道41号",
          "uid": "f6caf909c7a2e05032f71d38",
          "location": {
            "lng": 113.55350996434,
            "lat": 22.806673085386
          }
        },
        {
          "name": "沙县小吃(金沙路店)",
          "address": "海珠区工业大道北金沙路青蓝莓主题酒店对面",
          "uid": "c18e7a651c42907208f5eb51",
          "telephone": "13616949115",
          "location": {
            "lng": 113.26368301029,
            "lat": 23.096159931445
          }
        },
        {
          "name": "博济牙科(金沙路)",
          "address": "金沙路10号之3附近",
          "uid": "9e9874d101edbea248cc4a84",
          "telephone": "(020)84304409",
          "location": {
            "lng": 113.26209947733,
            "lat": 23.096360302009
          }
        },
        {
          "name": "金沙拉肠(金沙路店)",
          "address": "金沙街横沙村城西花园翠茵街110号铺",
          "uid": "73160ab1377dff483b221c51",
          "telephone": "13823534289",
          "location": {
            "lng": 113.21509501273,
            "lat": 23.162257989462
          }
        },
        {
          "name": "润兴送水(金沙路)",
          "address": "金洲金沙路138号一楼",
          "uid": "b4a9a0c9fe4b65551029352e",
          "telephone": "(020)84685006,(020)84685007",
          "location": {
            "lng": 113.55429041216,
            "lat": 22.814421047075
          }
        },
        {
          "name": "剑南春（金沙路店）",
          "address": "广东省广州市海珠区金沙路16-20号自编之14号",
          "uid": "16add8e386967656250bd017",
          "telephone": "020-34499985",
          "location": {
            "lng": 113.26145503296,
            "lat": 23.096244949768
          }
        },
        {
          "name": "农夫绿色水果（金沙路店）",
          "address": "金沙路16、20号首层之15号",
          "uid": "cab45b7fcfe32b554acc4a30",
          "telephone": "13556134579",
          "location": {
            "lng": 113.26148171263,
            "lat": 23.096329718716
          }
        },
        {
          "name": "忠信百货商店(金沙路)",
          "address": "金洲中围下街南巷5号",
          "uid": "f61365b99b126d0a8f1a893c",
          "location": {
            "lng": 113.55302335224,
            "lat": 22.810752418206
          }
        },
        {
          "name": "肯德基(金沙路餐厅)",
          "address": "广州市海珠区工业大道北76-80号富力家信商业中心（金沙路）1层",
          "uid": "691305232b77b811735e8086",
          "telephone": "4008823823",
          "location": {
            "lng": 113.26429421735,
            "lat": 23.09723699239
          }
        },
        {
          "name": "汉堡王(金沙路店)",
          "address": "广州市南沙区南沙街金沙路西侧星河盛世星河COCOGo购物中心一楼L1C-010、012；L1S-049号",
          "uid": "0b16cef32aea153ef603b842",
          "telephone": "(020)39002942",
          "location": {
            "lng": 113.55242615874,
            "lat": 22.81062890735
          }
        },
        {
          "name": "百果园(金沙路店)",
          "address": "金沙路6-14号",
          "uid": "38c7afdc20eede839cf779ee",
          "telephone": "(020)34487348",
          "location": {
            "lng": 113.26273727425,
            "lat": 23.096442162148
          }
        },
        {
          "name": "小四川(金沙路店)",
          "address": "金沙路附近",
          "uid": "3411ef2367abd20ec7f025e4",
          "location": {
            "lng": 113.55891381096,
            "lat": 22.823057545878
          }
        },
        {
          "name": "通达装潢(金沙路)",
          "address": "海庭一街与金沙路交叉口南100米",
          "uid": "88c71be2545be982c4f025e1",
          "location": {
            "lng": 113.55305425395,
            "lat": 22.811488150791
          }
        },
        {
          "name": "八佰伴(金沙路店)",
          "address": "海珠区金沙路(美景)",
          "uid": "23116913730deae4724b878e",
          "location": {
            "lng": 113.26230006895,
            "lat": 23.09602978599
          }
        },
        {
          "name": "绿草堂(金沙路店)",
          "address": "广州市南沙区近郊金洲金沙路42号(近金沙广场)",
          "uid": "2848ffd6683e041649cc4abe",
          "telephone": "(020)61922180",
          "location": {
            "lng": 113.55305119971,
            "lat": 22.809421609834
          }
        },
        {
          "name": "星艺装饰(金沙路)",
          "address": "广州市南沙区金沙路今洲广场1层",
          "uid": "febe11f2ac7729cf31f71d8f",
          "location": {
            "lng": 113.55252703845,
            "lat": 22.807350039979
          }
        },
        {
          "name": "福雪东北菜饺子馆(金沙路店)",
          "address": "金沙路49号（福苑旁）距凤凰新村站约530米",
          "uid": "010d181f463f3707c909f0d0",
          "telephone": "18665735806",
          "location": {
            "lng": 113.26144218719,
            "lat": 23.095966126033
          }
        },
        {
          "name": "成就地产(金沙路)",
          "address": "南沙区金沙路交通银行斜对面",
          "uid": "8bf26b49f7898beb3a13fd82",
          "telephone": "13602283132",
          "location": {
            "lng": 113.55301014715,
            "lat": 22.808582175223
          }
        },
        {
          "name": "东北烧烤(金沙路)",
          "address": "广东省广州市南沙区金沙路21附近",
          "uid": "41136fa0f6e354f29fe321fd",
          "location": {
            "lng": 113.55255758083,
            "lat": 22.807549927495
          }
        },
        {
          "name": "康乐幼儿园(金沙路)",
          "address": "金沙路1号附近",
          "uid": "dc3030d59064a63c364aaefc",
          "location": {
            "lng": 113.55305667938,
            "lat": 22.80793229483
          }
        },
        {
          "name": "乐婴岛金沙路旗舰店",
          "address": "广东省广州市海珠区金沙路16至20号首层商铺自编之十二",
          "uid": "9ea481535702f32a9cf7798b",
          "telephone": "18927543087",
          "location": {
            "lng": 113.26176997887,
            "lat": 23.096338029394
          }
        },
        {
          "name": "8008发廊(金沙路店)",
          "address": "金沙路41号首层",
          "uid": "c8f88f924ffb45056cc02c1c",
          "telephone": "(020)83489263",
          "location": {
            "lng": 113.26204000951,
            "lat": 23.096029370455
          }
        },
        {
          "name": "常德米粉（金沙路店）",
          "address": "南沙街道金沙路18号金基城四楼",
          "uid": "ce5d7153d1d49d4b3686f434",
          "telephone": "18820309740",
          "location": {
            "lng": 113.55349118975,
            "lat": 22.807953616087
          }
        },
        {
          "name": "太湖海鲜酒家(金沙路)",
          "address": "广州市海珠区工业大道北76-80号富力家信商业中心（金沙路）B1层",
          "uid": "8d96925c0601e35cc0f1cfee",
          "telephone": "(020)89602280",
          "location": {
            "lng": 113.2644413598,
            "lat": 23.097659254409
          }
        },
        {
          "name": "荔骏会(金沙路)",
          "address": "金沙路16-20号（近革新路）",
          "uid": "1eeed5464f38e4ebb5147f38",
          "telephone": "(020)84343558",
          "location": {
            "lng": 113.26135208715,
            "lat": 23.096327474833
          }
        },
        {
          "name": "力丰医药连锁(金沙路店)",
          "address": "金沙路16、20号首层商铺自编13号",
          "uid": "d5464cf83e2d044efda77854",
          "location": {
            "lng": 113.25969498298,
            "lat": 23.099178007021
          }
        },
        {
          "name": "丰泰堂大药房(金沙路)",
          "address": "金沙路10附近",
          "uid": "a3f21eee3b25005d2fb17e54",
          "location": {
            "lng": 113.26215921465,
            "lat": 23.09636129929
          }
        },
        {
          "name": "石花坊鲜花店(金沙路店)",
          "address": "广东省广州市海珠区金沙路10号首层商铺自编之八号",
          "uid": "6c78b2ff4d85fac2256e9880",
          "telephone": "4006907520",
          "location": {
            "lng": 113.26229881133,
            "lat": 23.096363709386
          }
        },
        {
          "name": "新日电动车(金沙路)",
          "address": "北塔7号",
          "uid": "81c229be8f6612ce2fb9083a",
          "location": {
            "lng": 113.55265001647,
            "lat": 22.809138023273
          }
        },
        {
          "name": "永视帮眼镜店(金沙路店)",
          "address": "广州市南沙区金洲商业街惠康街114号自贸城F1",
          "uid": "76a120f5036b4d6440ab9a15",
          "telephone": "(020)39091868",
          "location": {
            "lng": 113.55355074741,
            "lat": 22.808201642025
          }
        },
        {
          "name": "广东国旅(金沙路)",
          "address": "金洲村进港大道33号（今洲广场肯德基对面）",
          "uid": "57c56e3939f3509f363a71c0",
          "telephone": "(020)39090488",
          "location": {
            "lng": 113.55320696589,
            "lat": 22.806726389021
          }
        },
        {
          "name": "广州金十金沙路10号之三",
          "address": "广州市海珠区",
          "uid": "4fb41de809cd3b53b5f42fe2",
          "location": {
            "lng": 113.26222928248,
            "lat": 23.096033525804
          }
        },
        {
          "name": "Express特快店(金沙路店)",
          "address": "金沙路1-3号",
          "uid": "40ea41ce5e81c94d02ec0115",
          "location": {
            "lng": 113.26532852632,
            "lat": 23.096513800117
          }
        },
        {
          "name": "舒美居家饰(金沙路店)",
          "address": "金沙路16号附近",
          "uid": "486e2862c033045195f08c3c",
          "telephone": "18926124855",
          "location": {
            "lng": 113.26216999432,
            "lat": 23.096033027162
          }
        },
        {
          "name": "海庭五街与金沙路交叉口",
          "address": "广东省广州市南沙区",
          "uid": "7248ec68631079df43d63e9e",
          "location": {
            "lng": 113.55330577949,
            "lat": 22.813218114265
          }
        },
        {
          "name": "一哥酸菜鱼(金沙路店)",
          "address": "金沙路49号",
          "uid": "05133e76372865b2f1193720",
          "telephone": "(020)34078706",
          "location": {
            "lng": 113.26135397359,
            "lat": 23.095920001633
          }
        },
        {
          "name": "大行(折叠车金沙路店)",
          "address": "金沙路现代一街",
          "uid": "6e7f08e30313063fa2d23077",
          "telephone": "(020)84439476",
          "location": {
            "lng": 113.26337480167,
            "lat": 23.09657205788
          }
        },
        {
          "name": "时尚小鱼(金沙路)",
          "address": "沙园街道工业大道北103-28号",
          "uid": "3b75e2719b36819e0f0e6bf8",
          "location": {
            "lng": 113.26321580159,
            "lat": 23.096478978418
          }
        }
      ]
    }
  }
}