{
  "status": 0,
  "message": "ok",
  "type": 2,
  "info": {
    "copyright": {
      "text": "@2016 Baidu - Data",
      "imageUrl": "http://api.map.baidu.com/images/copyright_logo.png"
    }
  },
  "result": {
    "routes": [
      {
        "distance": 4933,
        "duration": 476,
        "steps": [
          {
            "area": 0,
            "direction": 0,
            "distance": 73,
            "duration": 23,
            "instructions": "从起点\u003c/b\u003e向正北方向出发,沿革新路\u003c/b\u003e行驶20米,过右侧的船舶大厦\u003c/font\u003e\u003c/b\u003e约50米后,右转\u003c/b\u003e进入金沙路\u003c/b\u003e",
            "path": "113.26100417343,23.095441636642;113.26100417343,23.095451609522;113.26092395474,23.09610009447",
            "pois": [
              {
                "detail": {
                  "instructions": "",
                  "position": 1
                },
                "location": {
                  "lng": 113.26118329554,
                  "lat": 23.095664696557
                },
                "name": "船舶大厦",
                "type": 106
              }
            ],
            "turn": 3,
            "type": 3,
            "stepOriginLocation": {
              "lng": 113.26100417343,
              "lat": 23.095441636642
            },
            "stepDestinationLocation": {
              "lng": 113.26092386491,
              "lat": 23.09610009447
            },
            "stepOriginInstruction": "从起点向正北方向出发 - 470米",
            "stepDestinationInstruction": "右转进入金沙路 - 470米",
            "traffic_condition": 1
          },
          {
            "area": 0,
            "direction": 3,
            "distance": 474,
            "duration": 65,
            "instructions": "沿金沙路\u003c/b\u003e行驶470米,右转\u003c/b\u003e进入工业大道北\u003c/b\u003e",
            "path": "113.2616712551,23.09611305915;113.26225919605,23.096123115087;113.26253820974,23.096147880946;113.26271760135,23.096170901555;113.26380374255,23.096349082595;113.26403290028,23.096412825475;113.26435179874,23.096498009849;113.26477031927,23.096614774683;113.26504933297,23.096689238181;113.2654678535,23.096805919741",
            "pois": [],
            "turn": 3,
            "type": 3,
            "stepOriginLocation": {
              "lng": 113.26092386491,
              "lat": 23.09610009447
            },
            "stepDestinationLocation": {
              "lng": 113.26546776367,
              "lat": 23.096806002847
            },
            "stepOriginInstruction": "",
            "stepDestinationInstruction": "右转进入工业大道北 - 540米",
            "traffic_condition": 1
          },
          {
            "area": 0,
            "direction": 5,
            "distance": 543,
            "duration": 34,
            "instructions": "沿工业大道北\u003c/b\u003e行驶520米,过左侧的沙园大厦\u003c/font\u003e\u003c/b\u003e朝鹤洞大桥/环城高速(西环)方向\u003c/b\u003e,靠左\u003c/b\u003e",
            "path": "113.26557762644,23.096647768001;113.2656175112,23.09660845858;113.26573725533,23.096440500014;113.26588700285,23.096232982383;113.26591691643,23.096193506625;113.26609657753,23.09595648562;113.26623626404,23.095778802695;113.26704464916,23.094701480603;113.26709450512,23.094642307834;113.26760348502,23.093990159006;113.26810249373,23.093357703728;113.26852164308,23.092823978941",
            "pois": [
              {
                "detail": {
                  "instructions": "",
                  "position": 0
                },
                "location": {
                  "lng": 113.2686610601,
                  "lat": 23.093215006108
                },
                "name": "沙园大厦",
                "type": 106
              }
            ],
            "turn": 9,
            "type": 3,
            "stepOriginLocation": {
              "lng": 113.26546776367,
              "lat": 23.096806002847
            },
            "stepDestinationLocation": {
              "lng": 113.26852173291,
              "lat": 23.092823064742
            },
            "stepOriginInstruction": "",
            "stepDestinationInstruction": "靠左 - 200米",
            "traffic_condition": 1
          },
          {
            "area": 0,
            "direction": 5,
            "distance": 200,
            "duration": 14,
            "instructions": "继续沿工业大道北\u003c/b\u003e行驶200米,朝鹤洞大桥/S81/环城高速(西环)方向\u003c/b\u003e,靠右\u003c/b\u003e进入鹤洞大桥\u003c/b\u003e",
            "path": "113.26963967412,23.091368982089",
            "pois": [],
            "turn": 10,
            "type": 3,
            "stepOriginLocation": {
              "lng": 113.26852173291,
              "lat": 23.092823064742
            },
            "stepDestinationLocation": {
              "lng": 113.26963967412,
              "lat": 23.091368982089
            },
            "stepOriginInstruction": "",
            "stepDestinationInstruction": "靠右进入鹤洞大桥 - 2.4公里",
            "traffic_condition": 1
          },
          {
            "area": 0,
            "direction": 5,
            "distance": 2433,
            "duration": 225,
            "instructions": "沿鹤洞大桥\u003c/b\u003e行驶2.4公里,直行\u003c/b\u003e进入鹤洞路\u003c/b\u003e",
            "path": "113.26966967752,23.091289445902;113.26969968093,23.091169933757;113.26971971314,23.091060311605;113.26971971314,23.091010362436;113.26971971314,23.090980442792;113.26969986059,23.090920271044;113.26968997923,23.090870238712;113.26967012668,23.090830013369;113.26965027413,23.090789788014;113.26962045038,23.090759452769;113.26960059783,23.090739256972;113.26955083171,23.090708672384;113.26947115201,23.090667615889;113.2692917604,23.090605200019;113.26905263147,23.090511950155;113.26888321105,23.090449617322;113.26878358897,23.090408311415;113.26875376523,23.090398005714;113.26871397029,23.090367504158;113.26856458209,23.090255471137;113.26852478715,23.090214996276;113.26849496341,23.090174687624;113.26846513967,23.090124322569;113.26844528712,23.090084097;113.2684155532,23.090013785336;113.26840567184,23.089963752663;113.26840567184,23.089913803082;113.26841573286,23.089824043389;113.26843576508,23.089694473503;113.26845579729,23.089574876813;113.26846576848,23.089535149744;113.26847573967,23.089475392896;113.26847573967,23.089415469798;113.2684758295,23.089345573336;113.26846594814,23.089285483958;113.26844609559,23.089225311441;113.26844609559,23.089205364745;113.26843621423,23.08916530512;113.26841636168,23.089125079261;113.26837656674,23.089074630697;113.26832689045,23.088994012689;113.26824730058,23.088892949219;113.26814776833,23.088771606465;113.26782886987,23.088607045567;113.26740037815,23.088400762376;113.26658318962,23.088088428071;113.26606504701,23.087910485287;113.26530768563,23.087698632498;113.26403218164,23.087328034751;113.2633049135,23.087066064157;113.2629861947,23.086930839921;113.2598579356,23.085647075504;113.25734753102,23.084612724377;113.25704875461,23.084487471348;113.25698910712,23.08446652657;113.2567799816,23.084372856827;113.25652108995,23.084248351601;113.25631196443,23.084144707976;113.25622240337,23.08410323388;113.25620255082,23.08409292769;113.25618269826,23.084082621499;113.25615287452,23.084072149078;113.25605334227,23.084010478141;113.25590404389,23.083917888565;113.25479840947,23.083268346779;113.25384216326,23.08269152774;113.25380236832,23.08267091514;113.25377254458,23.082650468768;113.25223841843,23.081723729481;113.25050486846,23.080674054372;113.2501462649,23.080488039342",
            "pois": [],
            "turn": 1,
            "type": 3,
            "stepOriginLocation": {
              "lng": 113.26963967412,
              "lat": 23.091368982089
            },
            "stepDestinationLocation": {
              "lng": 113.25014177337,
              "lat": 23.080482138057
            },
            "stepOriginInstruction": "",
            "stepDestinationInstruction": "直行进入鹤洞路 - 1.2公里",
            "traffic_condition": 1
          },
          {
            "area": 0,
            "direction": 7,
            "distance": 1210,
            "duration": 112,
            "instructions": "沿鹤洞路\u003c/b\u003e行驶950米,过右侧的欧曼顿酒店-商务中心\u003c/font\u003e\u003c/b\u003e约260米后,到达终点\u003c/b\u003e",
            "path": "113.25011194963,23.080451634225;113.25002238857,23.080400184968;113.24993282751,23.080338761677;113.24988306139,23.080308008462;113.24965399348,23.080164299427;113.24949463408,23.080081764323;113.24865768284,23.079588048738;113.24840867255,23.079434115491;113.24820942839,23.079310935517;113.24789061976,23.079085853328;113.24772128918,23.078973228972;113.24693401423,23.078500870581;113.24653543607,23.078254758145;113.24648566995,23.078224087566;113.2462664834,23.078100823354;113.24601738329,23.077967086125;113.24588784763,23.077885214604;113.24560883394,23.077701107396;113.24546932709,23.077589146815;113.24535973382,23.077507607536;113.24518034221,23.077375033372;113.24505080656,23.077243207143;113.24445271475,23.076674590749;113.24411378408,23.076289831981;113.24396430604,23.076117774881;113.24367523133,23.075753794417;113.24338615662,23.075399870462;113.24331644811,23.075309020408;113.24321682603,23.075167716449;113.2429077191,23.074763586299;113.24279812583,23.074612224197;113.2426086732,23.074369761865;113.24235939342,23.074046588896;113.2421599696,23.073784093402;113.24197051696,23.07352168051;113.24184089148,23.073350118554;113.24166141004,23.073117877842;113.24161164391,23.073057365521",
            "pois": [
              {
                "detail": {
                  "instructions": "",
                  "position": 1
                },
                "location": {
                  "lng": 113.24294481912,
                  "lat": 23.075091744729
                },
                "name": "欧曼顿酒店-商务中心",
                "type": 106
              }
            ],
            "turn": 0,
            "type": 3,
            "stepOriginLocation": {
              "lng": 113.25014177337,
              "lat": 23.080482138057
            },
            "stepDestinationLocation": {
              "lng": 113.24160823035,
              "lat": 23.073054290031
            },
            "stepDestinationInstruction": "到达终点",
            "traffic_condition": 1
          }
        ],
        "toll": 0,
        "originLocation": {
          "lng": 113.26100417343,
          "lat": 23.095441636642
        },
        "destinationLocation": {
          "lng": 113.24160823035,
          "lat": 23.073054290031
        }
      }
    ],
    "origin": {
      "area_id": 257,
      "bid": "18011735505204412415",
      "cname": "广州市",
      "uid": "50fb64ff068ff25de9f85376",
      "wd": "船舶大厦",
      "originPt": {
        "lng": 113.2609996819,
        "lat": 23.09544263393
      }
    },
    "destination": {
      "area_id": 257,
      "bid": "10215069",
      "cname": "广州市",
      "uid": "8a7f41d8fee6635996f08c92",
      "wd": "花地大道中",
      "destinationPt": {
        "lng": 113.24160526594,
        "lat": 23.073051630148
      }
    },
    "taxi": {
      "detail": [
        {
          "desc": "全天",
          "km_price": "2.6",
          "start_price": "10.0",
          "total_price": "17"
        }
      ],
      "distance": 4933,
      "duration": 477,
      "remark": "全程4.9公里;2.5公里起步；燃油附加费0.0元；里程超过35.0公里，超过部分每公里收3.9元。"
    },
    "traffic_condition": 1
  }
}