{
  "status": 0,
  "message": "ok",
  "type": 1,
  "info": {
    "copyright": {
      "text": "@2016 Baidu - Data",
      "imageUrl": "http://api.map.baidu.com/images/copyright_logo.png"
    }
  },
  "result": {
    "originInfo": {
      "area_id": 257,
      "wd": "云台花园",
      "uid": ""
    },
    "destinationInfo": {
      "area_id": 257,
      "wd": "宝发棋牌",
      "uid": ""
    },
    "origin": {
      "cityName": "广州市",
      "listType": 0,
      "content": [
        {
          "name": "云台花园",
          "address": "白云山风景区南麓(近白云索道)",
          "uid": "4edf9fbfface0594cd06a4a5",
          "telephone": "(020)37229187",
          "location": {
            "lng": 113.30088803975,
            "lat": 23.16159304862
          }
        },
        {
          "name": "云台花园",
          "address": "",
          "uid": "d83680b221eb29c1c4f025b0",
          "location": {
            "lng": 113.30186800123,
            "lat": 23.16224145943
          }
        },
        {
          "name": "云台花园-南门",
          "address": "云山南路与广园中路交汇处",
          "uid": "2a1eaa89104c032283a00ca3",
          "location": {
            "lng": 113.30071538543,
            "lat": 23.161707430312
          }
        },
        {
          "name": "云台花园-北门",
          "address": "云山南路白云山南门旁",
          "uid": "3c77c76c3e4773e442d63e79",
          "telephone": "(020)37226736",
          "location": {
            "lng": 113.30253113036,
            "lat": 23.166656482791
          }
        },
        {
          "name": "云台花园罗马柱廊",
          "address": "广园中路801号白云山风景名胜区白云山风景名胜区-云台花园附近",
          "uid": "52ef82f1bfa32ca12b06cebd",
          "location": {
            "lng": 113.30005522071,
            "lat": 23.164055763453
          }
        },
        {
          "name": "云台花园-东门",
          "address": "云山南路白云山南门附近",
          "uid": "bcf951db56d82106130daa1c",
          "telephone": "(020)37226736",
          "location": {
            "lng": 113.30222121496,
            "lat": 23.164619104694
          }
        },
        {
          "name": "云台花园生态谷",
          "address": "广州市白云区",
          "uid": "ab4a53fcb7d4841214b54b78",
          "telephone": "(020)37226736",
          "location": {
            "lng": 113.30095181944,
            "lat": 23.16847595919
          }
        },
        {
          "name": "云台花园-停车场",
          "address": "云山南路白云山索道附近",
          "uid": "72aa2513f65f1539077ce805",
          "location": {
            "lng": 113.30081455836,
            "lat": 23.161581170196
          }
        },
        {
          "name": "云台花园(东北门)",
          "address": "广东省广州市白云区云泉路163号大院",
          "uid": "d7588073fc41c68d3310af9d",
          "location": {
            "lng": 113.30233260484,
            "lat": 23.164710724254
          }
        },
        {
          "name": "云台花园(东南门)",
          "address": "广园中路801号云台花园",
          "uid": "f1546e8120f950608b2fb5c4",
          "location": {
            "lng": 113.30066939219,
            "lat": 23.161779946758
          }
        },
        {
          "name": "云台花园白云索道售票处",
          "address": "广东省广州市白云区云台花园内",
          "uid": "45148552c9726602ae080f52",
          "location": {
            "lng": 113.30204999793,
            "lat": 23.163500975479
          }
        },
        {
          "name": "云台花园总站",
          "address": "",
          "uid": "9493863007aa60390482c2cf",
          "location": {
            "lng": 113.30178598594,
            "lat": 23.162343962206
          }
        },
        {
          "name": "云台花园南门售票处",
          "address": "云山南路",
          "uid": "d3fefa7220486a89f02d8361",
          "location": {
            "lng": 113.30081482785,
            "lat": 23.161895242011
          }
        },
        {
          "name": "云台花园公交站场",
          "address": "",
          "uid": "3c13ebce47265be28bfc0666",
          "location": {
            "lng": 113.30207029963,
            "lat": 23.162187549915
          }
        },
        {
          "name": "云台花园售票处",
          "address": "云山南路白云山南门旁",
          "uid": "58ae9da2b70776228936ee00",
          "telephone": "(020)37226736",
          "location": {
            "lng": 113.30253400494,
            "lat": 23.16648346303
          }
        },
        {
          "name": "凯丽文农产品(云台花园店)",
          "address": "广东省广州市越秀区",
          "uid": "83a25f20b9ae671bb45f1ec0",
          "location": {
            "lng": 113.30283412881,
            "lat": 23.164916058159
          }
        },
        {
          "name": "云台花园北门售票处",
          "address": "云山南路白云山南门旁",
          "uid": "7910b27cb3c39db32811d101",
          "location": {
            "lng": 113.30252017103,
            "lat": 23.166703662408
          }
        },
        {
          "name": "云台花园东门售票处",
          "address": "云山南路白云山南门附近",
          "uid": "f28daa87cc969bd07dc876a6",
          "telephone": "(020)37226736",
          "location": {
            "lng": 113.30222121496,
            "lat": 23.164619104694
          }
        },
        {
          "name": "金贵饭店",
          "address": "广州市越秀区广园中路云台花园侧金贵停车场内",
          "uid": "923ffd004e4c7eaed82f28ea",
          "telephone": "(020)37228923",
          "location": {
            "lng": 113.30223998954,
            "lat": 23.162539996468
          }
        },
        {
          "name": "白云山国家级风景名胜区",
          "address": "广园中路白云山南门售票处（云台花园直上600米处）",
          "uid": "0d89822800d2b7e84f3a5976",
          "telephone": "(020)37222222",
          "location": {
            "lng": 113.30851123997,
            "lat": 23.177984091927
          }
        },
        {
          "name": "盆满钵满",
          "address": "广园中路云台花园旁",
          "uid": "231169138e1197e4724b878a",
          "telephone": "(020)37226888",
          "location": {
            "lng": 113.29995011897,
            "lat": 23.161249321489
          }
        },
        {
          "name": "白云食街(横枝岗路)",
          "address": "越秀区广园东西坑田螺墩二街1号(云台花园对面)",
          "uid": "e3a7fd13a5f2284b29b97cf8",
          "telephone": "18819292088",
          "location": {
            "lng": 113.30180691646,
            "lat": 23.161493784835
          }
        },
        {
          "name": "沙河粉村(白云山二店)",
          "address": "广州白云区广园中路白云山(近云台花园)",
          "uid": "dffd631c677918a539221c8e",
          "telephone": "(020)37227888,(020)37226888",
          "location": {
            "lng": 113.300379509,
            "lat": 23.161599361628
          }
        },
        {
          "name": "山西名优土特产广州总经销",
          "address": "云台花园公交车总站出口旁停车场内102(云台花园或白云山索道或金贵饭店或各卿饮食)",
          "uid": "ac351fa7a63a65bff8f0cb45",
          "telephone": "15360869776,13168801699",
          "location": {
            "lng": 113.30203876911,
            "lat": 23.162682038061
          }
        },
        {
          "name": "和卿饮食",
          "address": "广州越秀区广园东路金贵停车场内(云台花园公交总站旁)",
          "uid": "22a592c51daacba82a02e1e5",
          "telephone": "(020)37229886",
          "location": {
            "lng": 113.3027385491,
            "lat": 23.163556047364
          }
        },
        {
          "name": "菩竹水农家驴庄(白云山店)",
          "address": "越秀区广园东路西坑村田螺墩二街3号(云台花园对面(云台花园和白云索道)",
          "uid": "359a994a69d6b06421026220",
          "telephone": "(020)37229271",
          "location": {
            "lng": 113.30180700629,
            "lat": 23.161494781627
          }
        },
        {
          "name": "茂林修竹",
          "address": "云山南路云台花园内",
          "uid": "ecdeef00dd3f97a7d22dd657",
          "location": {
            "lng": 113.30234302518,
            "lat": 23.166007844414
          }
        },
        {
          "name": "搏弈亭",
          "address": "云山南路云台花园内",
          "uid": "3fbbf8576207644dc16c1435",
          "location": {
            "lng": 113.30206347251,
            "lat": 23.16525329681
          }
        },
        {
          "name": "浣纱亭",
          "address": "云山南路云台花园内",
          "uid": "a49eccb0d73afb9507fef5f8",
          "location": {
            "lng": 113.30218150985,
            "lat": 23.164970714136
          }
        },
        {
          "name": "中国皮界",
          "address": "广州白云区云台花园西侧云翠谷2号楼",
          "uid": "9b65d3b857a4b3ba00ff2d2a",
          "telephone": "(020)26298393",
          "location": {
            "lng": 113.29786101967,
            "lat": 23.195418060005
          }
        },
        {
          "name": "醉华苑",
          "address": "广园中路801号云台花园附近",
          "uid": "ac856bcf340e948efa42b266",
          "location": {
            "lng": 113.29954336623,
            "lat": 23.163431450306
          }
        },
        {
          "name": "花盘",
          "address": "广园中路801号云台花园附近",
          "uid": "d1a63474845c31584c554748",
          "location": {
            "lng": 113.30043511411,
            "lat": 23.163041045432
          }
        },
        {
          "name": "喷泉广场",
          "address": "广园中路801号云台花园附近",
          "uid": "d71c38261898618e223bf2f5",
          "location": {
            "lng": 113.2994465289,
            "lat": 23.162862372519
          }
        },
        {
          "name": "紫燕百味鸡(长腰岭店)",
          "address": "广州市越秀区广园东路长腰岭一街1号(近云台花园)",
          "uid": "3a1552ae5e588da72811d1e2",
          "telephone": "13104890060",
          "location": {
            "lng": 113.30461474999,
            "lat": 23.161365447865
          }
        },
        {
          "name": "广园中路小区",
          "address": "广园中路（云台花园南侧）",
          "uid": "5547407accc2a99e4afd3fb7",
          "location": {
            "lng": 113.27348891323,
            "lat": 23.165240006633
          }
        },
        {
          "name": "巍璞",
          "address": "云山南路云台花园内",
          "uid": "422ddefeb8990ac1c4f02547",
          "location": {
            "lng": 113.30031375304,
            "lat": 23.164992892163
          }
        },
        {
          "name": "听潺轩",
          "address": "云山南路云台花园内",
          "uid": "aee447fdecaf7eded4851f77",
          "location": {
            "lng": 113.30195118432,
            "lat": 23.165302802707
          }
        },
        {
          "name": "姑嫂坟",
          "address": "云山南路云台花园内",
          "uid": "dcaa37c3899a0fd7a8059dab",
          "location": {
            "lng": 113.30131832809,
            "lat": 23.164120553632
          }
        },
        {
          "name": "白云区交运机动车驾驶员培训之训中心白云山招生部",
          "address": "广园中路云台花园侧金贵停车场内",
          "uid": "b535024b8597554c4bcc4af2",
          "telephone": "(020)83662425",
          "location": {
            "lng": 113.30223918107,
            "lat": 23.162538418227
          }
        },
        {
          "name": "山顶观光亭",
          "address": "云山南路云台花园内",
          "uid": "d71fadc25f92047d0bf5ebcb",
          "location": {
            "lng": 113.29804130959,
            "lat": 23.164647761771
          }
        },
        {
          "name": "广州市宝狮机电贸易有限公司(东升大厦南)",
          "address": "白云区广园中路633号(云台花园)",
          "uid": "16c03a62d2143a8842d63efa",
          "telephone": "(020)36045958",
          "location": {
            "lng": 113.28860434072,
            "lat": 23.166787721825
          }
        },
        {
          "name": "逸心亭",
          "address": "云山南路云台花园内",
          "uid": "e98628ea3d67c70ab4265583",
          "location": {
            "lng": 113.30172022997,
            "lat": 23.164955679591
          }
        },
        {
          "name": "春舍",
          "address": "云山南路云台花园内",
          "uid": "8e0cc4ebbfadf4b2ad31e5d1",
          "location": {
            "lng": 113.30159958754,
            "lat": 23.164637129581
          }
        },
        {
          "name": "岩石园",
          "address": "广园中路801号云台花园附近",
          "uid": "d8fbb11451098c0ad8131801",
          "location": {
            "lng": 113.3005970786,
            "lat": 23.164649339987
          }
        },
        {
          "name": "空静",
          "address": "云山南路云台花园内",
          "uid": "8ffd0d2532ff794e0869d954",
          "location": {
            "lng": 113.3010640178,
            "lat": 23.164892135778
          }
        },
        {
          "name": "花城明珠",
          "address": "云山南路云台花园(南门)附近",
          "uid": "d57b05342c8a3f9eeb1e97d7",
          "location": {
            "lng": 113.30044373784,
            "lat": 23.161655597226
          }
        },
        {
          "name": "公厕",
          "address": "云山南路云台花园(南门)附近",
          "uid": "eae72167afbaf74ad42ce238",
          "location": {
            "lng": 113.29725268718,
            "lat": 23.157454973204
          }
        },
        {
          "name": "云石",
          "address": "白云山路云台花园(东南门)附近",
          "uid": "af4a0f60f16dc300bfa8222a",
          "location": {
            "lng": 113.30144121628,
            "lat": 23.164629072374
          }
        },
        {
          "name": "三人舞姬雕像",
          "address": "广园中路801号云台花园附近",
          "uid": "685f17795b215ba1ae31e564",
          "location": {
            "lng": 113.29944706788,
            "lat": 23.16335851944
          }
        },
        {
          "name": "园圃园",
          "address": "云山南路云台花园内",
          "uid": "f99c8fcda5c2b7fab6f42f20",
          "location": {
            "lng": 113.30172022997,
            "lat": 23.16491564284
          }
        }
      ]
    },
    "destination": {
      "cityName": "广州市",
      "listType": 0,
      "content": [
        {
          "name": "宝发棋牌",
          "address": "宝华路90号6楼",
          "uid": "8360af002a5eea312b3a9f90",
          "telephone": "(020)81386791",
          "location": {
            "lng": 113.24848404038,
            "lat": 23.121428421068
          }
        },
        {
          "name": "宝发棋牌",
          "address": "江南大道中广东土产大厦对面",
          "uid": "e46a9095441ceaef76e5b671",
          "telephone": "(020)89092091",
          "location": {
            "lng": 113.27786428988,
            "lat": 23.109456534592
          }
        }
      ]
    }
  }
}