{
  "status": 0,
  "message": "ok",
  "type": 1,
  "info": {
    "copyright": {
      "text": "@2016 Baidu - Data",
      "imageUrl": "http://api.map.baidu.com/images/copyright_logo.png"
    }
  },
  "result": {
    "originInfo": {
      "area_id": 257,
      "wd": "贵贤上品公寓",
      "uid": ""
    },
    "destinationInfo": {
      "area_id": 257,
      "wd": "富力路",
      "uid": ""
    },
    "origin": {
      "cityName": "广州市",
      "listType": 0,
      "content": [
        {
          "name": "贵贤上品公寓",
          "address": "华贵路1号贵贤上品",
          "uid": "aeb7d92183c8dc38ca09f0e1",
          "telephone": "(020)84416018",
          "location": {
            "lng": 113.24812211309,
            "lat": 23.126701857419
          }
        }
      ]
    },
    "destination": {
      "cityName": "广州市",
      "listType": 0,
      "content": [
        {
          "name": "富力路",
          "address": "广东省广州市荔湾区",
          "uid": "4e924ddf46f798e550e5c57d",
          "location": {
            "lng": 113.24381375004,
            "lat": 23.140125336702
          }
        },
        {
          "name": "富力路",
          "address": "广东省广州市增城区",
          "uid": "3c7656223da7fcbc87420ec7",
          "location": {
            "lng": 113.83171760611,
            "lat": 23.311871676355
          }
        },
        {
          "name": "南岸路/富力路(路口)",
          "address": "广东省广州市荔湾区",
          "uid": "b8a5467bb40ada02ed74f8f6",
          "location": {
            "lng": 113.23801797272,
            "lat": 23.140445773403
          }
        },
        {
          "name": "富力路小区",
          "address": "广东省广州市荔湾区南岸路与富力路交汇处",
          "uid": "d9fe0fcebf5c12d6f7b9165d",
          "location": {
            "lng": 113.24224800354,
            "lat": 23.139635084497
          }
        },
        {
          "name": "南源花园(富力路)",
          "address": "广州市荔湾区富力路30-32号",
          "uid": "606289fd1a24224da2046419",
          "telephone": "(020)81940132",
          "location": {
            "lng": 113.24147114893,
            "lat": 23.140195123345
          }
        },
        {
          "name": "阳光家园(富力路)",
          "address": "增城市荔城镇菜园中路93号",
          "uid": "5342bcb044e5f327eedfca3f",
          "location": {
            "lng": 113.83324499497,
            "lat": 23.312522004083
          }
        },
        {
          "name": "宏缘超市(富力路)",
          "address": "荔湾区富力路1号1层108号",
          "uid": "d6c5d991e49b6ee830169b14",
          "location": {
            "lng": 113.24133047429,
            "lat": 23.140212403841
          }
        },
        {
          "name": "熊猫国旅(富力路店)",
          "address": "广东省广州市荔湾区富力路30-32号",
          "uid": "21e82c1b5fc87d7132870a3a",
          "telephone": "(020)87248992,15920445303",
          "location": {
            "lng": 113.24173938296,
            "lat": 23.140041592681
          }
        },
        {
          "name": "中国酒鬼酒(富力路)",
          "address": "田间道30号自编20楼A6号",
          "uid": "c65595bbfd21b33bca1b95ab",
          "location": {
            "lng": 113.23870679339,
            "lat": 23.140563081122
          }
        },
        {
          "name": "福建蒸饺王(富力路店)",
          "address": "富力路42-1号101房自编105号铺",
          "uid": "89b2dca01b7f84208936eec8",
          "telephone": "18520512754",
          "location": {
            "lng": 113.24333306676,
            "lat": 23.140038684902
          }
        },
        {
          "name": "德奈福洗衣(富力路)",
          "address": "富力路24-5附近",
          "uid": "2714caf8201a321eabf0cdfb",
          "telephone": "13428811220",
          "location": {
            "lng": 113.24042776708,
            "lat": 23.140253361932
          }
        },
        {
          "name": "益街坊美食(富力路店)",
          "address": "荔湾区广州市荔湾区富力路42-1号(南海中学旁)",
          "uid": "193510e2fa7a2fe904fef578",
          "telephone": "13719213880",
          "location": {
            "lng": 113.24338274306,
            "lat": 23.140051811448
          }
        },
        {
          "name": "潮汕牛肉店(富力路店)",
          "address": "富力路42-1号101房自编103号铺",
          "uid": "cb20a396b0a5cdcbf4c59c9c",
          "telephone": "18318630334",
          "location": {
            "lng": 113.24320550738,
            "lat": 23.140137964764
          }
        },
        {
          "name": "青青文海(富力路)",
          "address": "广东省广州市荔湾区富力路44附近",
          "uid": "9d9a44e16f379f1b6dc02c77",
          "location": {
            "lng": 113.24390340093,
            "lat": 23.13979659127
          }
        },
        {
          "name": "烤鱼吧青岛多彩扎啤9098(富力路店)",
          "address": "富力路田间道30号",
          "uid": "24d937e6cbcd905bcac3db4f",
          "telephone": "13794323153",
          "location": {
            "lng": 113.23848033057,
            "lat": 23.140521707732
          }
        },
        {
          "name": "鼎湖山泉(富力路店)",
          "address": "南岸富力路30号之六铺",
          "uid": "31aa60413bff3f8f2b11d1f5",
          "telephone": "(020)81815210",
          "location": {
            "lng": 113.24190206608,
            "lat": 23.140455576743
          }
        },
        {
          "name": "富力路与开园中路交叉口",
          "address": "广东省广州市增城市增城区",
          "uid": "36f70930278dbc618d77272a",
          "location": {
            "lng": 113.83557151641,
            "lat": 23.311859562539
          }
        },
        {
          "name": "珍奥富力路健康体验馆",
          "address": "广州市荔湾区",
          "uid": "1ff3a9ef805a196d9322e092",
          "location": {
            "lng": 113.24175941517,
            "lat": 23.14045881683
          }
        },
        {
          "name": "中国铁通(富力路营业点)",
          "address": "荔湾区富力路24-7号",
          "uid": "f0348723efbc43d9a1acc475",
          "telephone": "(020)62756638",
          "location": {
            "lng": 113.24023328394,
            "lat": 23.140269146994
          }
        },
        {
          "name": "景田百岁山桶装水(富力路店)",
          "address": "荔湾区富力路24号之十(近中山八路)",
          "uid": "397d3bbf506942bf0ab93a60",
          "telephone": "020-26283293",
          "location": {
            "lng": 113.24020849071,
            "lat": 23.140264245317
          }
        },
        {
          "name": "万洁汽车美容中心(富力路)",
          "address": "富力路20号附近",
          "uid": "b1c556e8cf2b9b0cb4265513",
          "telephone": "(020)81955350",
          "location": {
            "lng": 113.23926553941,
            "lat": 23.140588087924
          }
        },
        {
          "name": "增城市人口和计划生育服务站(富力路)",
          "address": "广州市增城市",
          "uid": "9c914e3fec6e006bc7f025fb",
          "location": {
            "lng": 113.83503235344,
            "lat": 23.312104327777
          }
        },
        {
          "name": "安顺汽车驾驶员培训有限公司(富力路分部)",
          "address": "广东省广州市荔湾区富力路32-2号",
          "uid": "da4e40065f43d1c4cae33c17",
          "telephone": "020-81959399|13556000028",
          "location": {
            "lng": 113.2413505065,
            "lat": 23.140414618715
          }
        },
        {
          "name": "富力新居",
          "address": "荔湾区荔湾南岸富力路36号",
          "uid": "d6c5d991e4916ee830169b1e",
          "location": {
            "lng": 113.24317209041,
            "lat": 23.139821681296
          }
        },
        {
          "name": "广州市荔湾区汇龙小学",
          "address": "富力路32-2号",
          "uid": "75d0881a3772d04d3a04b10c",
          "telephone": "020-81960648",
          "location": {
            "lng": 113.2411696776,
            "lat": 23.139141341119
          }
        },
        {
          "name": "广州市南海中学",
          "address": "广州市荔湾区南岸富力路56号(高中部)",
          "uid": "be9d9c5319ffdbee40ab9ace",
          "telephone": "(020)81349526",
          "location": {
            "lng": 113.24415268071,
            "lat": 23.139871113619
          }
        },
        {
          "name": "市政东苑",
          "address": "南岸路富力路44号大院",
          "uid": "97a9c133c935b09546e27483",
          "location": {
            "lng": 113.24363507707,
            "lat": 23.139147821357
          }
        },
        {
          "name": "东方美女子会所",
          "address": "中国广东省广州市荔湾区富力路36号富力新居内12号铺",
          "uid": "9fab1f89e67cda81bea240ac",
          "telephone": "13719370373",
          "location": {
            "lng": 113.2428862496,
            "lat": 23.139513538889
          }
        },
        {
          "name": "广东省有线电视",
          "address": "广东省广州市荔湾区南岸富力路36号",
          "uid": "a735bceb24bb9796b6f42fbb",
          "location": {
            "lng": 113.24267703425,
            "lat": 23.140111047051
          }
        },
        {
          "name": "广电网络广东有线一分部营业厅",
          "address": "广东省广州市荔湾区富力路36号之九602室",
          "uid": "35d119c2dbe74d52843304b4",
          "location": {
            "lng": 113.24288633943,
            "lat": 23.140073578251
          }
        },
        {
          "name": "鑫福记酒楼",
          "address": "富力路35-39",
          "uid": "aafcf7692d4adbe61ce9992d",
          "telephone": "(020)32828993",
          "location": {
            "lng": 113.83226593179,
            "lat": 23.311706397349
          }
        },
        {
          "name": "荔鑫豪华门窗工程加工部",
          "address": "广东省广州市增城市富力路35号",
          "uid": "44103d3aa169885176e5b636",
          "location": {
            "lng": 113.83262660145,
            "lat": 23.311694366489
          }
        },
        {
          "name": "增城市农业机械质量投诉监督站",
          "address": "富力路10",
          "uid": "1b0ce4df90a447442902e16a",
          "location": {
            "lng": 113.83402490381,
            "lat": 23.312055042881
          }
        },
        {
          "name": "油泰爷增城市油泰爷润滑油经营部",
          "address": "富力路15",
          "uid": "7f0cff3f475aed42364aaeaf",
          "location": {
            "lng": 113.83304512199,
            "lat": 23.311731786607
          }
        },
        {
          "name": "增城区动物卫生监督所",
          "address": "富力路10号",
          "uid": "fe74aef5b3c0f1e5095cb371",
          "location": {
            "lng": 113.83386410712,
            "lat": 23.312004928254
          }
        },
        {
          "name": "正果云吞",
          "address": "增城区富力路人源百货旁",
          "uid": "2c4ddc68f7e932f58f1a8993",
          "location": {
            "lng": 113.83623096248,
            "lat": 23.311694034603
          }
        },
        {
          "name": "乐家嘉",
          "address": "广东省广州市增城区增城区富力路19",
          "uid": "b948e18dfcbcf882fb2d61ef",
          "location": {
            "lng": 113.83312507118,
            "lat": 23.311742241006
          }
        },
        {
          "name": "食得福食馆",
          "address": "增城区富力路7号",
          "uid": "e6295cec6899b41d2902e18b",
          "telephone": "(020)82442036",
          "location": {
            "lng": 113.83591592674,
            "lat": 23.311691462488
          }
        },
        {
          "name": "麦记乳品经营部",
          "address": "富力路30-之7号附近",
          "uid": "bfd356516d9b723acc06a42a",
          "telephone": "(020)88278921",
          "location": {
            "lng": 113.24184322707,
            "lat": 23.140393931998
          }
        },
        {
          "name": "e度时尚",
          "address": "南岸富力路南源花园门口正对面",
          "uid": "c57ae9cd0e6cfc373fe23120",
          "location": {
            "lng": 113.24184295758,
            "lat": 23.140394015077
          }
        },
        {
          "name": "慧兴墙纸",
          "address": "富力路2号101附近",
          "uid": "9d2c062a73e15599f03cba04",
          "telephone": "18319072198",
          "location": {
            "lng": 113.23786445231,
            "lat": 23.140041426522
          }
        },
        {
          "name": "宜佳烟酒商行",
          "address": "富力路2号附近",
          "uid": "9ad45c71231bd1fbe9f8538e",
          "telephone": "(020)81814341",
          "location": {
            "lng": 113.23817885924,
            "lat": 23.140266571537
          }
        },
        {
          "name": "厚兴包子店",
          "address": "广东省广州市荔湾区富力路30号",
          "uid": "26444f3ac0f3fdcc3517dccc",
          "location": {
            "lng": 113.24184322707,
            "lat": 23.140393931998
          }
        },
        {
          "name": "广州市煤建公司建筑材料购销部",
          "address": "富力路30号自编之7",
          "uid": "f92370831c5bfe598f1a89fe",
          "telephone": "020-81948913",
          "location": {
            "lng": 113.24198983053,
            "lat": 23.140445773403
          }
        },
        {
          "name": "国安金门分店",
          "address": "富力路2号105铺",
          "uid": "f03d0dfcedfcc75021022037",
          "telephone": "13668933946",
          "location": {
            "lng": 113.23809307106,
            "lat": 23.140300717113
          }
        },
        {
          "name": "神采高尔夫",
          "address": "广东省广州市荔湾区富力路2附近",
          "uid": "4651376c3c7605def4e73b89",
          "telephone": "13760728355,18926130789",
          "location": {
            "lng": 113.23806809817,
            "lat": 23.140216474727
          }
        },
        {
          "name": "尚体运动健康精品馆",
          "address": "广东省广州市荔湾区富力路2附近",
          "uid": "c72e0f48a383c230c4f50d2d",
          "location": {
            "lng": 113.23727426559,
            "lat": 23.138593593707
          }
        },
        {
          "name": "童真衣趣",
          "address": "富力路3号附近",
          "uid": "7b5113c01707e013ebe582a1",
          "location": {
            "lng": 113.24142326925,
            "lat": 23.140150592824
          }
        },
        {
          "name": "广州市捷购贸易有限公司",
          "address": "富力路2号-112",
          "uid": "491b270cc4f412e817948e8d",
          "location": {
            "lng": 113.23827758301,
            "lat": 23.140197532645
          }
        },
        {
          "name": "中共西焦社区总支部委员会",
          "address": "富力路42-1号",
          "uid": "7f686710471becd6725e8036",
          "location": {
            "lng": 113.24351452447,
            "lat": 23.140031124675
          }
        }
      ]
    }
  }
}